vending_machine.v
`timescale 1ns/1ps

module vending_machine(
    input clk,
    input rst,
    input coin5,
    input coin10,
    output reg dispense,
    output reg change
);

parameter S0  = 2'b00;
parameter S5  = 2'b01;
parameter S10 = 2'b10;
parameter S15 = 2'b11;

reg [1:0] state;
reg [1:0] next_state;

// State Register
always @(posedge clk or posedge rst)
begin
    if (rst)
        state <= S0;
    else
        state <= next_state;
end

// Next-State Logic
always @(*)
begin
    case(state)

        S0:
        begin
            if (coin5)
                next_state = S5;
            else if (coin10)
                next_state = S10;
            else
                next_state = S0;
        end

        S5:
        begin
            if (coin5)
                next_state = S10;
            else if (coin10)
                next_state = S15;
            else
                next_state = S5;
        end

        S10:
        begin
            if (coin5 || coin10)
                next_state = S15;
            else
                next_state = S10;
        end

        S15:
            next_state = S0;

        default:
            next_state = S0;

    endcase
end

// Output Logic
always @(*)
begin
    dispense = 0;
    change   = 0;

    case(state)

        S15:
        begin
            dispense = 1;

            if (coin10)
                change = 1;
        end

    endcase
end

endmodule

vending_machine_tb.v
`timescale 1ns/1ps

module vending_machine_tb;

reg clk;
reg rst;
reg coin5;
reg coin10;

wire dispense;
wire change;

vending_machine uut (
    .clk(clk),
    .rst(rst),
    .coin5(coin5),
    .coin10(coin10),
    .dispense(dispense),
    .change(change)
);

// Clock Generation
always #5 clk = ~clk;

initial
begin
    clk = 0;
    rst = 1;
    coin5 = 0;
    coin10 = 0;

    #20;
    rst = 0;

    // Insert Rs.5
    #10 coin5 = 1;
    #10 coin5 = 0;

    // Insert Rs.10
    #10 coin10 = 1;
    #10 coin10 = 0;

    // Wait
    #30;

    // Insert Rs.10
    #10 coin10 = 1;
    #10 coin10 = 0;

    // Insert another Rs.10
    #10 coin10 = 1;
    #10 coin10 = 0;

    #50;
    $finish;
end

initial
begin
    $monitor(
        "Time=%0t coin5=%b coin10=%b dispense=%b change=%b",
        $time, coin5, coin10, dispense, change
    );
end

initial
begin
    $dumpfile("vending_machine.vcd");
    $dumpvars(0, vending_machine_tb);
end

endmodule

vending_machine.vcd
$date
	Tue Jun 16 13:12:49 2026
$end
$version
	Icarus Verilog
$end
$timescale
	1ps
$end
$scope module vending_machine_tb $end
$var wire 1 ! dispense $end
$var wire 1 " change $end
$var reg 1 # clk $end
$var reg 1 $ coin10 $end
$var reg 1 % coin5 $end
$var reg 1 & rst $end
$scope module uut $end
$var wire 1 # clk $end
$var wire 1 $ coin10 $end
$var wire 1 % coin5 $end
$var wire 1 & rst $end
$var parameter 2 ' S0 $end
$var parameter 2 ( S10 $end
$var parameter 2 ) S15 $end
$var parameter 2 * S5 $end
$var reg 1 " change $end
$var reg 1 ! dispense $end
$var reg 2 + next_state [1:0] $end
$var reg 2 , state [1:0] $end
$upscope $end
$upscope $end
$enddefinitions $end
$comment Show the parameter values. $end
$dumpall
b1 *
b11 )
b10 (
b0 '
$end
#0
$dumpvars
b0 ,
b0 +
1&
0%
0$
0#
0"
0!
$end
#5000
1#
#10000
0#
#15000
1#
#20000
0#
0&
#25000
1#
#30000
b1 +
0#
1%
#35000
b10 +
b1 ,
1#
#40000
b1 +
0#
0%
#45000
1#
#50000
b11 +
0#
1$
#55000
1"
1!
b0 +
b11 ,
1#
#60000
0"
1!
0#
0$
#65000
0!
b0 ,
1#
#70000
0#
#75000
1#
#80000
0#
#85000
1#
#90000
0#
#95000
1#
#100000
b10 +
0#
1$
#105000
b11 +
b10 ,
1#
#110000
b10 +
0#
0$
#115000
1#
#120000
b11 +
0#
1$
#125000
1"
1!
b0 +
b11 ,
1#
#130000
0"
1!
0#
0$
#135000
0!
b0 ,
1#
